{"chunk_definitions":[{"row":13,"row_count":1,"visible":true,"expansion_state":0,"options":{"engine":"r","label":"setup","include":false},"document_id":"38F42CD0","chunk_id":"csetup_chunk","chunk_label":"setup"},{"row":22,"row_count":1,"visible":true,"expansion_state":0,"options":{"engine":"r","label":"unnamed-chunk-235"},"document_id":"38F42CD0","chunk_id":"c7r3hgly6wkkq","chunk_label":"unnamed-chunk-1"},{"row":35,"row_count":1,"visible":true,"expansion_state":0,"options":{"engine":"r","label":"unnamed-chunk-236"},"document_id":"38F42CD0","chunk_id":"c5570popzro70","chunk_label":"unnamed-chunk-2"},{"row":53,"row_count":1,"visible":true,"expansion_state":0,"options":{"engine":"r","label":"unnamed-chunk-237"},"document_id":"38F42CD0","chunk_id":"cejac8dxswhw2","chunk_label":"unnamed-chunk-3"},{"row":73,"row_count":1,"visible":true,"expansion_state":0,"options":{"engine":"r","label":"unnamed-chunk-238"},"document_id":"38F42CD0","chunk_id":"cu956n7fndxhc","chunk_label":"unnamed-chunk-4"},{"row":97,"row_count":1,"visible":true,"expansion_state":0,"options":{"engine":"r","label":"unnamed-chunk-239"},"document_id":"38F42CD0","chunk_id":"chihzny3p66u3","chunk_label":"unnamed-chunk-5"},{"row":155,"row_count":1,"visible":true,"expansion_state":0,"options":{"engine":"r","label":"unnamed-chunk-240"},"document_id":"38F42CD0","chunk_id":"c8clywq8k49u1","chunk_label":"unnamed-chunk-6"},{"row":181,"row_count":1,"visible":true,"expansion_state":0,"options":{"engine":"r","label":"unnamed-chunk-241"},"document_id":"38F42CD0","chunk_id":"c15u3h4a3e7lu","chunk_label":"unnamed-chunk-7"},{"row":189,"row_count":1,"visible":true,"expansion_state":0,"options":{"engine":"r","label":"unnamed-chunk-242"},"document_id":"38F42CD0","chunk_id":"coand158vxmsi","chunk_label":"unnamed-chunk-8"},{"row":218,"row_count":1,"visible":true,"expansion_state":0,"options":{"engine":"r","label":"unnamed-chunk-243"},"document_id":"38F42CD0","chunk_id":"ck8yvxk58ji8n","chunk_label":"unnamed-chunk-9"},{"row":276,"row_count":1,"visible":true,"expansion_state":0,"options":{"engine":"r","label":"unnamed-chunk-249"},"document_id":"38F42CD0","chunk_id":"cxgclgwzh5o4q","chunk_label":"unnamed-chunk-10"},{"row":337,"row_count":1,"visible":true,"expansion_state":0,"options":{"engine":"r","label":"unnamed-chunk-279"},"document_id":"38F42CD0","chunk_id":"cwgc1a5f1dgkf","chunk_label":"unnamed-chunk-11"}],"doc_write_time":1660113116,"working_dir":null,"default_chunk_options":{"echo":true},"chunk_rendered_width":643}